{
  "Info": {
    "맛집": {
      "group": "장소",
      "fields": ["장소명", "주소", "대표 메뉴/특징", "유효기간/이벤트 기간"]
    },
    "카페": {
      "group": "장소",
      "fields": ["장소명", "주소", "대표 메뉴/특징", "유효기간/이벤트 기간"]
    },
    "공부": {
      "group": "학업/업무",
      "fields": ["주제/시험명", "기관/학교", "마감일", "주요 포인트"]
    },
    "공고": {
      "group": "학업/업무",
      "fields": ["공고명", "기관/회사", "마감일", "주요 포인트"]
    },
    "취업": {
      "group": "학업/업무",
      "fields": ["회사/직무", "기관", "마감일", "주요 포인트"]
    },
    "필기": {
      "group": "학업/업무",
      "fields": ["주제", "내용", "날짜", "메모"]
    },
    "뉴스": {
      "group": "라이프스타일",
      "fields": ["주제", "내용 요약", "날짜", "메모"]
    },
    "문화생활": {
      "group": "라이프스타일",
      "fields": ["활동명", "장소", "날짜", "메모"]
    },
    "운동/건강": {
      "group": "라이프스타일",
      "fields": ["활동명", "내용", "날짜", "메모"]
    },
    "기타": {
      "group": "라이프스타일",
      "fields": ["제목", "내용", "날짜", "메모"]
    },
    "쿠폰": {
      "group": "소비",
      "fields": ["브랜드/가게명", "혜택 요약", "유효기간", "조건/제한"]
    }
  },
  "Contents": {
    "글": {
      "group": null,
      "fields": ["주요 문구", "tone", "topic"]
    },
    "짤": {
      "group": null,
      "fields": ["주요 문구", "tone", "topic"]
    }
  },
  "Social": {
    "채팅": {
      "group": null,
      "fields": ["앱 이름", "참여자", "마지막 대화 요약", "할 일"]
    },
    "사진": {
      "group": null,
      "fields": ["앱 이름", "참여자", "날짜", "메모"]
    }
  },
  "Log": {
    "기록": {
      "group": null,
      "fields": ["기록 제목", "수치/결과", "날짜", "메모"]
    },
    "활동": {
      "group": null,
      "fields": ["활동명", "장소", "날짜", "메모"]
    }
  },
  "Music": {
    "음악": {
      "group": null,
      "fields": ["title", "artist", "앨범명", "무드"]
    }
  },
  "Art": {
    "미술": {
      "group": null,
      "fields": ["작품/전시명", "아티스트", "전시 장소", "무드"]
    }
  },
  "Unknown": {
    "기타": {
      "group": null,
      "fields": ["제목", "내용", "날짜", "메모"]
    }
  }
}
